ray_chunkit_chung_gum_gum_pistol/__init__.py
ray_chunkit_chung_gum_gum_pistol/__main__.py
ray_chunkit_chung_gum_gum_pistol/main.py
ray_chunkit_chung_gum_gum_pistol-0.1.2.dist-info/entry_points.txt
ray_chunkit_chung_gum_gum_pistol-0.1.2.dist-info/LICENSE
ray_chunkit_chung_gum_gum_pistol-0.1.2.dist-info/METADATA
ray_chunkit_chung_gum_gum_pistol-0.1.2.dist-info/WHEEL
ray_chunkit_chung_gum_gum_pistol-0.1.2.dist-info/RECORD
