Metadata-Version: 2.1
Name: ray-chunkit-chung-gum-gum-pistol
Version: 0.1.2
Summary: 
Author: ray-chunkit-chung
Author-email: ray.chunkit.chung@gmail.com
Requires-Python: >=3.11,<4.0
Classifier: Programming Language :: Python :: 3
Classifier: Programming Language :: Python :: 3.11
Requires-Dist: pytest[all] (>=7.2.1,<8.0.0)
Requires-Dist: typer[all] (>=0.7.0,<0.8.0)
